revengai/__init__.py
revengai/api_client.py
revengai/api_response.py
revengai/configuration.py
revengai/exceptions.py
revengai/py.typed
revengai/rest.py
revengai/api/__init__.py
revengai/api/analyses_comments_api.py
revengai/api/analyses_core_api.py
revengai/api/analyses_dynamic_execution_api.py
revengai/api/analyses_results_metadata_api.py
revengai/api/analyses_security_checks_api.py
revengai/api/authentication_users_api.py
revengai/api/binaries_api.py
revengai/api/collections_api.py
revengai/api/config_api.py
revengai/api/external_sources_api.py
revengai/api/firmware_api.py
revengai/api/functions_ai_decompilation_api.py
revengai/api/functions_block_comments_api.py
revengai/api/functions_core_api.py
revengai/api/functions_data_types_api.py
revengai/api/functions_decompilation_api.py
revengai/api/functions_renaming_history_api.py
revengai/api/models_api.py
revengai/api/search_api.py
revengai/models/__init__.py
revengai/models/additional_details_status_response.py
revengai/models/addr.py
revengai/models/ai_decompilation_rating.py
revengai/models/ai_unstrip_request.py
revengai/models/analysis_access_info.py
revengai/models/analysis_config.py
revengai/models/analysis_create_request.py
revengai/models/analysis_create_response.py
revengai/models/analysis_detail_response.py
revengai/models/analysis_function_mapping.py
revengai/models/analysis_function_matching_request.py
revengai/models/analysis_functions.py
revengai/models/analysis_functions_list.py
revengai/models/analysis_record.py
revengai/models/analysis_scope.py
revengai/models/analysis_strings_response.py
revengai/models/analysis_strings_status_response.py
revengai/models/analysis_tags.py
revengai/models/analysis_update_request.py
revengai/models/analysis_update_tags_request.py
revengai/models/analysis_update_tags_response.py
revengai/models/app_api_rest_v2_analyses_enums_dynamic_execution_status.py
revengai/models/app_api_rest_v2_analyses_enums_order_by.py
revengai-3.0.0.dist-info/METADATA
revengai-3.0.0.dist-info/WHEEL
revengai-3.0.0.dist-info/licenses/LICENSE.md
revengai-3.0.0.dist-info/RECORD
