Metadata-Version: 2.4
Name: revengai
Version: 3.0.0
Summary: RevEng.AI API
Project-URL: Repository, https://github.com/RevEngAI/sdk-python
License-Expression: MIT
License-File: LICENSE.md
Keywords: RevEng.AI API
Requires-Python: >=3.10
Requires-Dist: lazy-imports<2,>=1
Requires-Dist: pydantic>=2
Requires-Dist: python-dateutil>=2.8.2
Requires-Dist: typing-extensions>=4.7.1
Requires-Dist: urllib3<3.0.0,>=2.1.0
